<?xml version="1.0" encoding="UTF-8" standalone="yes"?>
<QualityMeasureDocument xmlns="urn:hl7-org:v3" xmlns:xsi="http://www.w3.org/2001/XMLSchema-instance" xsi:schemaLocation="urn:hl7-org:v3 ../../HQMF_N1_XSD_EXT/schemas/EMeasure_N1.xsd urn:hhs-cql:hqmf-n1-extensions:v1 ../../HQMF_N1_XSD_EXT/schemas/hhs-cql-hqmfn1-ext-v1.xsd">
         
      <!--
            **************************************************************
            Measure Details Section
            **************************************************************
        -->
         
      <typeId extension="POQM_HD000001UV02" root="2.16.840.1.113883.1.3"/>
   <templateId>
      <item root="2.16.840.1.113883.10.20.28.1.2" extension="2018-05-01"/>
   </templateId>
   <id root="40280582-5b4d-ee92-015b-8d05cb5601a3"/>
   <code code="57024-2" codeSystem="2.16.840.1.113883.6.1">
      <displayName value="Health Quality Measure Document"/>
   </code>
   <title value="TestCMS55v5"/>
   <text value=""/>
   <statusCode code="COMPLETED"/>
   <setId root="2999e82b-abe7-41e6-adee-42bb67f1c88b"/>
   <versionNumber value="0.0.001"/>
   <custodian>
      <responsibleParty classCode="ASSIGNED">
         <representedResponsibleOrganization classCode="ORG" determinerCode="INSTANCE">
            <id>
               <item root=""/>
            </id>
            <name>
               <item>
                  <part value=""/>
               </item>
            </name>
         </representedResponsibleOrganization>
      </responsibleParty>
   </custodian>
   <relatedDocument typeCode="COMP">
      <expressionDocument>
         <id root="DFAAF6C1-0609-49C7-BCEA-8EEDFB65DCFF"/>
         <text mediaType="application/cql">
            <reference value="TestCMS55v5-0.0.001.cql"/>
            <translation mediaType="application/elm+xml">
               <reference value="TestCMS55v5-0.0.001.xml"/>
            </translation>
         </text>
         <setId root="http://example.org/ecqms/libraries/" extension="TestCMS55v5"/>
         <versionNumber value="0.0.001"/>
      </expressionDocument>
   </relatedDocument>
   <controlVariable>
      <measurePeriod>
         <id extension="measureperiod" root="f347406c-56a0-4515-aba1-c85ca1f384e0"/>
         <code code="MSRTP" codeSystem="2.16.840.1.113883.5.4">
            <originalText value="Measurement Period"/>
         </code>
         <value xsi:type="PIVL_TS">
            <phase highClosed="true" lowClosed="true">
               <low value="20170101"/>
               <width unit="a" value="1" xsi:type="PQ"/>
            </phase>
            <period unit="a" value="1"/>
         </value>
      </measurePeriod>
   </controlVariable>
   <subjectOf>
      <measureAttribute>
         <code nullFlavor="OTH">
            <originalText value="eMeasure Identifier (Measure Authoring Tool)"/>
         </code>
         <value mediaType="text/plain" value="" xsi:type="ED"/>
      </measureAttribute>
   </subjectOf>
   <subjectOf>
      <measureAttribute>
         <code nullFlavor="OTH">
            <originalText value="NQF Number"/>
         </code>
         <value mediaType="text/plain" value="" xsi:type="ED"/>
      </measureAttribute>
   </subjectOf>
   <subjectOf>
      <measureAttribute>
         <code code="COPY" codeSystem="2.16.840.1.113883.5.4">
            <displayName value="Copyright"/>
         </code>
         <value mediaType="text/plain" value="" xsi:type="ED"/>
      </measureAttribute>
   </subjectOf>
   <subjectOf>
      <measureAttribute>
         <code code="DISC" codeSystem="2.16.840.1.113883.5.4">
            <displayName value="Disclaimer"/>
         </code>
         <value mediaType="text/plain" value="" xsi:type="ED"/>
      </measureAttribute>
   </subjectOf>
   <subjectOf>
      <measureAttribute>
         <code code="MSRSCORE" codeSystem="2.16.840.1.113883.5.4">
            <displayName value="Measure Scoring"/>
         </code>
         <value code="CONTVAR" codeSystem="2.16.840.1.113883.1.11.20367" xsi:type="CD">
            <displayName value="Continuous Variable"/>
         </value>
      </measureAttribute>
   </subjectOf>
   <subjectOf>
      <measureAttribute>
         <code code="STRAT" codeSystem="2.16.840.1.113883.5.4">
            <displayName value="Stratification"/>
         </code>
         <value mediaType="text/plain" value="" xsi:type="ED"/>
      </measureAttribute>
   </subjectOf>
   <subjectOf>
      <measureAttribute>
         <code code="MSRADJ" codeSystem="2.16.840.1.113883.5.4">
            <displayName value="Risk Adjustment"/>
         </code>
         <value mediaType="text/plain" value="" xsi:type="ED"/>
      </measureAttribute>
   </subjectOf>
   <subjectOf>
      <measureAttribute>
         <code code="MSRAGG" codeSystem="2.16.840.1.113883.5.4">
            <displayName value="Rate Aggregation"/>
         </code>
         <value mediaType="text/plain" value="" xsi:type="ED"/>
      </measureAttribute>
   </subjectOf>
   <subjectOf>
      <measureAttribute>
         <code code="RAT" codeSystem="2.16.840.1.113883.5.4">
            <displayName value="Rationale"/>
         </code>
         <value mediaType="text/plain" value="" xsi:type="ED"/>
      </measureAttribute>
   </subjectOf>
   <subjectOf>
      <measureAttribute>
         <code code="CRS" codeSystem="2.16.840.1.113883.5.4">
            <displayName value="Clinical Recommendation Statement"/>
         </code>
         <value mediaType="text/plain" value="" xsi:type="ED"/>
      </measureAttribute>
   </subjectOf>
   <subjectOf>
      <measureAttribute>
         <code code="IDUR" codeSystem="2.16.840.1.113883.5.4">
            <displayName value="Improvement Notation"/>
         </code>
         <value mediaType="text/plain" value="" xsi:type="ED"/>
      </measureAttribute>
   </subjectOf>
   <subjectOf>
      <measureAttribute>
         <code code="REF" codeSystem="2.16.840.1.113883.5.4">
            <displayName value="Reference"/>
         </code>
         <value mediaType="text/plain" xsi:type="ED"/>
      </measureAttribute>
   </subjectOf>
   <subjectOf>
      <measureAttribute>
         <code code="DEF" codeSystem="2.16.840.1.113883.5.4">
            <displayName value="Definition"/>
         </code>
         <value mediaType="text/plain" xsi:type="ED"/>
      </measureAttribute>
   </subjectOf>
   <subjectOf>
      <measureAttribute>
         <code code="GUIDE" codeSystem="2.16.840.1.113883.5.4">
            <displayName value="Guidance"/>
         </code>
         <value mediaType="text/plain" value="" xsi:type="ED"/>
      </measureAttribute>
   </subjectOf>
   <subjectOf>
      <measureAttribute>
         <code code="TRANF" codeSystem="2.16.840.1.113883.5.4">
            <displayName value="Transmission Format"/>
         </code>
         <value mediaType="text/plain" value="" xsi:type="ED"/>
      </measureAttribute>
   </subjectOf>
   <subjectOf>
      <measureAttribute>
         <code code="IPOP" codeSystem="2.16.840.1.113883.5.4">
            <displayName value="Initial Population"/>
         </code>
         <value mediaType="text/plain" value="" xsi:type="ED"/>
      </measureAttribute>
   </subjectOf>
   <subjectOf>
      <measureAttribute>
         <code code="MSRPOPL" codeSystem="2.16.840.1.113883.5.4">
            <displayName value="Measure Population"/>
         </code>
         <value mediaType="text/plain" value="" xsi:type="ED"/>
      </measureAttribute>
   </subjectOf>
   <subjectOf>
      <measureAttribute>
         <code code="MSRPOPLEX" codeSystem="2.16.840.1.113883.5.4">
            <displayName value="Measure Population Exclusions"/>
         </code>
         <value mediaType="text/plain" value="" xsi:type="ED"/>
      </measureAttribute>
   </subjectOf>
   <subjectOf>
      <measureAttribute>
         <code nullFlavor="OTH">
            <displayName value="Measure Observations"/>
         </code>
         <value mediaType="text/plain" value="" xsi:type="ED"/>
      </measureAttribute>
   </subjectOf>
   <subjectOf>
      <measureAttribute>
         <code code="SDE" codeSystem="2.16.840.1.113883.5.4">
            <displayName value="Supplemental Data Elements"/>
         </code>
         <value mediaType="text/plain" value="" xsi:type="ED"/>
      </measureAttribute>
   </subjectOf>
   <componentOf>
      <qualityMeasureSet classCode="ACT">
         <id root=""/>
         <title value=""/>
      </qualityMeasureSet>
   </componentOf>
   <!--Data Criteria Section-->
   <component>
      <dataCriteriaSection>
         <templateId>
            <item root="2.16.840.1.113883.10.20.28.2.6" extension="2017-08-01"/>
         </templateId>
         <code code="57025-9" codeSystem="2.16.840.1.113883.6.1"/>
         <title value="Data Criteria Section"/>
         <text/>
         <entry typeCode="DRIV">
            <localVariableName value="EmergencyDepartmentVisit_EncounterPerformed_gJzbU"/>
            <encounterCriteria classCode="ENC" moodCode="EVN">
               <templateId>
                  <item root="2.16.840.1.113883.10.20.28.4.5" extension="2017-08-01"/>
               </templateId>
               <id extension="EmergencyDepartmentVisit_EncounterPerformed"
                   root="2dec421a-e0df-4195-a48e-0f8c1ff2f49e"/>
               <code valueSet="2.16.840.1.113883.3.117.1.7.1.292">
                  <displayName value="Emergency Department Visit SNOMEDCT Value Set"/>
               </code>
               <title value="Encounter, Performed"/>
               <statusCode code="COMPLETED"/>
            </encounterCriteria>
         </entry>
         <entry typeCode="DRIV">
            <localVariableName value="Payer_PatientCharacteristicPayer_eqIC2"/>
            <observationCriteria classCode="OBS" moodCode="EVN">
               <templateId>
                  <item extension="2017-05-01" root="2.16.840.1.113883.10.20.28.4.58"/>
               </templateId>
               <id extension="Payer_PatientCharacteristicPayer"
                   root="dcdac254-2436-4f8d-9a98-76cd2a99b2c2"/>
               <code code="48768-6" codeSystem="2.16.840.1.113883.6.1" codeSystemName="LOINC">
                  <displayName value="Payer"/>
               </code>
               <title value="Patient Characteristic Payer"/>
               <statusCode code="COMPLETED"/>
               <value valueSet="2.16.840.1.114222.4.11.3591" xsi:type="CD">
                  <displayName value="Payer Source of Payment Typology Value Set"/>
               </value>
            </observationCriteria>
         </entry>
         <entry typeCode="DRIV">
            <localVariableName value="ONCAdministrativeSex_PatientCharacteristicSex_VZy5x"/>
            <observationCriteria classCode="OBS" moodCode="EVN">
               <templateId>
                  <item extension="2017-05-01" root="2.16.840.1.113883.10.20.28.4.55"/>
               </templateId>
               <id extension="ONCAdministrativeSex_PatientCharacteristicSex"
                   root="7ea97fdb-9f21-42d8-b6d2-57397a819b9b"/>
               <code code="263495000" codeSystem="2.16.840.1.113883.6.96" codeSystemName="SNOMED CT">
                  <displayName value="Gender"/>
               </code>
               <title value="Patient Characteristic Sex"/>
               <statusCode code="COMPLETED"/>
               <value valueSet="2.16.840.1.113762.1.4.1" xsi:type="CD">
                  <displayName value="ONC Administrative Sex Administrative Sex Value Set"/>
               </value>
            </observationCriteria>
         </entry>
         <entry typeCode="DRIV">
            <localVariableName value="Ethnicity_PatientCharacteristicEthnicity_NyXCA"/>
            <observationCriteria classCode="OBS" moodCode="EVN">
               <templateId>
                  <item root="2.16.840.1.113883.10.20.28.4.56" extension="2017-05-01"/>
               </templateId>
               <id extension="Ethnicity_PatientCharacteristicEthnicity"
                   root="b6d93b8b-fe28-478b-9dec-74453dc93e2c"/>
               <code code="54133-4" codeSystem="2.16.840.1.113883.6.1" codeSystemName="LOINC">
                  <displayName value="Ethnicity"/>
               </code>
               <title value="Patient Characteristic Ethnicity"/>
               <statusCode code="COMPLETED"/>
               <value valueSet="2.16.840.1.114222.4.11.837" xsi:type="CD">
                  <displayName value="Ethnicity CDC Value Set"/>
               </value>
            </observationCriteria>
         </entry>
         <entry typeCode="DRIV">
            <localVariableName value="Race_PatientCharacteristicRace_ipyv1"/>
            <observationCriteria classCode="OBS" moodCode="EVN">
               <templateId>
                  <item root="2.16.840.1.113883.10.20.28.4.59" extension="2017-05-01"/>
               </templateId>
               <id extension="Race_PatientCharacteristicRace"
                   root="d038f64a-21dd-470e-90de-f2a8fec9fe85"/>
               <code code="32624-9" codeSystem="2.16.840.1.113883.6.1" codeSystemName="LOINC">
                  <displayName value="Race"/>
               </code>
               <title value="Patient Characteristic Race"/>
               <statusCode code="COMPLETED"/>
               <value valueSet="2.16.840.1.114222.4.11.836" xsi:type="CD">
                  <displayName value="Race CDC Value Set"/>
               </value>
            </observationCriteria>
         </entry>
      </dataCriteriaSection>
   </component>
   <component>
      <populationCriteriaSection>
         <templateId>
            <item root="2.16.840.1.113883.10.20.28.2.7" extension="2017-08-01"/>
         </templateId>
         <id extension="PopulationCriteria1" root="EBBF7CE9-5BAC-46BE-87D1-2173923F5EC9"/>
         <code code="57026-7" codeSystem="2.16.840.1.113883.6.1"/>
         <title value="Population Criteria Section"/>
         <text/>
         <component typeCode="COMP">
            <initialPopulationCriteria classCode="OBS" moodCode="EVN">
               <id extension="initialPopulation" root="4B34D088-C762-4150-890F-C7CAE0593F63"/>
               <code code="IPOP" codeSystem="2.16.840.1.113883.5.4" codeSystemName="Act Code"/>
               <precondition typeCode="PRCN">
                  <criteriaReference classCode="OBS" moodCode="EVN">
                     <id extension="TestCMS55v5.&quot;Initial Population&quot;"
                         root="DFAAF6C1-0609-49C7-BCEA-8EEDFB65DCFF"/>
                  </criteriaReference>
               </precondition>
            </initialPopulationCriteria>
         </component>
         <component typeCode="COMP">
            <measurePopulationCriteria classCode="OBS" moodCode="EVN">
               <id extension="measurePopulation" root="0276D90F-87A1-44CA-86CC-4A35DD1D708A"/>
               <code code="MSRPOPL" codeSystem="2.16.840.1.113883.5.4" codeSystemName="Act Code"/>
               <precondition typeCode="PRCN">
                  <criteriaReference classCode="OBS" moodCode="EVN">
                     <id extension="TestCMS55v5.&quot;Measure Population&quot;"
                         root="DFAAF6C1-0609-49C7-BCEA-8EEDFB65DCFF"/>
                  </criteriaReference>
               </precondition>
            </measurePopulationCriteria>
         </component>
         <component typeCode="COMP">
            <measurePopulationExclusionCriteria classCode="OBS" moodCode="EVN">
               <id extension="measurePopulationExclusions"
                   root="20C5657D-B0AD-4C15-A8A0-5D4E2BCB38F7"/>
               <code code="MSRPOPLEX" codeSystem="2.16.840.1.113883.5.4" codeSystemName="Act Code"/>
               <precondition typeCode="PRCN">
                  <criteriaReference classCode="OBS" moodCode="EVN">
                     <id extension="TestCMS55v5.&quot;Measure Population Exclusions&quot;"
                         root="DFAAF6C1-0609-49C7-BCEA-8EEDFB65DCFF"/>
                  </criteriaReference>
               </precondition>
            </measurePopulationExclusionCriteria>
         </component>
         <component typeCode="COMP">
            <stratifierCriteria>
               <id extension="Stratifiers" root="F8EB3BCE-C313-49F0-B441-83F9B060FBEC"/>
               <code code="STRAT" codeSystem="2.16.840.1.113883.5.4" codeSystemName="Act Code"/>
               <precondition typeCode="PRCN">
                  <criteriaReference classCode="OBS" moodCode="EVN">
                     <id extension="TestCMS55v5.&quot;Stratification 1&quot;"
                         root="DFAAF6C1-0609-49C7-BCEA-8EEDFB65DCFF"/>
                  </criteriaReference>
               </precondition>
            </stratifierCriteria>
         </component>
         <component typeCode="COMP">
            <stratifierCriteria>
               <id extension="Stratifiers" root="754820C0-C019-4E90-9C8C-2A93A42544A7"/>
               <code code="STRAT" codeSystem="2.16.840.1.113883.5.4" codeSystemName="Act Code"/>
               <precondition typeCode="PRCN">
                  <criteriaReference classCode="OBS" moodCode="EVN">
                     <id extension="TestCMS55v5.&quot;Stratification 2&quot;"
                         root="DFAAF6C1-0609-49C7-BCEA-8EEDFB65DCFF"/>
                  </criteriaReference>
               </precondition>
            </stratifierCriteria>
         </component>
         <component typeCode="COMP">
            <stratifierCriteria>
               <id extension="Stratifiers" root="645B9831-53BD-4F68-8B33-95F8F02B0B42"/>
               <code code="STRAT" codeSystem="2.16.840.1.113883.5.4" codeSystemName="Act Code"/>
               <precondition typeCode="PRCN">
                  <criteriaReference classCode="OBS" moodCode="EVN">
                     <id extension="TestCMS55v5.&quot;Stratification 3&quot;"
                         root="DFAAF6C1-0609-49C7-BCEA-8EEDFB65DCFF"/>
                  </criteriaReference>
               </precondition>
            </stratifierCriteria>
         </component>
         <component typeCode="COMP">
            <stratifierCriteria>
               <id extension="Stratifiers" root="F1BC700D-D184-44E6-836B-4A94BF4DAC26"/>
               <code code="STRAT" codeSystem="2.16.840.1.113883.5.4" codeSystemName="Act Code"/>
               <precondition typeCode="PRCN">
                  <criteriaReference classCode="OBS" moodCode="EVN">
                     <id extension="TestCMS55v5.&quot;SDE Ethnicity&quot;"
                         root="DFAAF6C1-0609-49C7-BCEA-8EEDFB65DCFF"/>
                  </criteriaReference>
               </precondition>
               <component typeCode="COMP">
                  <measureAttribute>
                     <code code="SDE" codeSystem="2.16.840.1.113883.5.4"
                        codeSystemName="Act Code"/>
                     <value mediaType="text/plain" value="Supplemental Data Elements" 
                        xsi:type="ED"/>
                  </measureAttribute>
               </component>
            </stratifierCriteria>
         </component>
         <component typeCode="COMP">
            <stratifierCriteria>
               <id extension="Stratifiers" root="CCFD703B-CEF9-488A-87E6-1867CA6C01DC"/>
               <code code="STRAT" codeSystem="2.16.840.1.113883.5.4" codeSystemName="Act Code"/>
               <precondition typeCode="PRCN">
                  <criteriaReference classCode="OBS" moodCode="EVN">
                     <id extension="TestCMS55v5.&quot;SDE Payer&quot;" root="DFAAF6C1-0609-49C7-BCEA-8EEDFB65DCFF"/>
                  </criteriaReference>
               </precondition>
               <component typeCode="COMP">
                  <measureAttribute>
                     <code code="SDE" codeSystem="2.16.840.1.113883.5.4" codeSystemName="Act Code"/>
                     <value mediaType="text/plain" value="Supplemental Data Elements" xsi:type="ED"/>
                  </measureAttribute>
               </component>
            </stratifierCriteria>
         </component>
         <component typeCode="COMP">
            <stratifierCriteria>
               <id extension="Stratifiers" root="97920C2A-2654-45D6-916B-65E7E98E301B"/>
               <code code="STRAT" codeSystem="2.16.840.1.113883.5.4" codeSystemName="Act Code"/>
               <precondition typeCode="PRCN">
                  <criteriaReference classCode="OBS" moodCode="EVN">
                     <id extension="TestCMS55v5.&quot;SDE Race&quot;" root="DFAAF6C1-0609-49C7-BCEA-8EEDFB65DCFF"/>
                  </criteriaReference>
               </precondition>
               <component typeCode="COMP">
                  <measureAttribute>
                     <code code="SDE" codeSystem="2.16.840.1.113883.5.4" codeSystemName="Act Code"/>
                     <value mediaType="text/plain" value="Supplemental Data Elements" xsi:type="ED"/>
                  </measureAttribute>
               </component>
            </stratifierCriteria>
         </component>
         <component typeCode="COMP">
            <stratifierCriteria>
               <id extension="Stratifiers" root="12C0E990-7A74-4020-BE61-AD2F550693F5"/>
               <code code="STRAT" codeSystem="2.16.840.1.113883.5.4" codeSystemName="Act Code"/>
               <precondition typeCode="PRCN">
                  <criteriaReference classCode="OBS" moodCode="EVN">
                     <id extension="TestCMS55v5.&quot;SDE Sex&quot;" root="DFAAF6C1-0609-49C7-BCEA-8EEDFB65DCFF"/>
                  </criteriaReference>
               </precondition>
               <component typeCode="COMP">
                  <measureAttribute>
                     <code code="SDE" codeSystem="2.16.840.1.113883.5.4" codeSystemName="Act Code"/>
                     <value mediaType="text/plain" value="Supplemental Data Elements" xsi:type="ED"/>
                  </measureAttribute>
               </component>
            </stratifierCriteria>
         </component>
      </populationCriteriaSection>
   </component>
   <component>
      <measureObservationSection>
         <templateId>
            <item root="2.16.840.1.113883.10.20.28.2.4" extension="2018-05-01"/>
         </templateId>
         <id extension="MeasureObservations" root="B525A408-F6C1-4755-97CF-E08346F3751E"/>
         <code code="57027-5" codeSystem="2.16.840.1.113883.6.1" codeSystemName="LOINC"/>
         <title value="Measure Observation Section"/>
         <text/>
         <!--Definition for Measure Observation 1-->
         <definition>
            <measureObservationDefinition classCode="OBS" moodCode="DEF">
               <id extension="Measure Observation" 
                   root="8A9A47CF-45A4-4385-923C-5A045D8EA9F8"/>
               <code code="AGGREGATE" codeSystem="2.16.840.1.113883.5.4"/>
               <value nullFlavor="DER" xsi:type="INT">
                  <expression value="TestCMS55v5.&quot;Measure Observation&quot;"/>
               </value>
               <methodCode>
                  <item code="MEDIAN" codeSystem="2.16.840.1.113883.5.84"/>
               </methodCode>
               <component typeCode="COMP">
                  <!-- This criteriaReference is a reference to the measure population criteria by id (root and extension attributes) within the target population group -->
                  <criteriaReference classCode="OBS" moodCode="EVN">
                    <!-- Points to the extension and root, rather than the name to ensure unique identification of the criteria -->
                    <id extension="measurePopulation" root="0276D90F-87A1-44CA-86CC-4A35DD1D708A"/>
				  </criteriaReference>
               </component>
            </measureObservationDefinition>
         </definition>
      </measureObservationSection>
   </component>
</QualityMeasureDocument>